musichelper/Deezer.py
musichelper/MusicHelper.py
musichelper/SoundCloud.py
musichelper/YTM.py
musichelper/__init__.py
musichelper/exceptions.py
musichelper/util.py
musichelper/constants/__init__.py
musichelper/constants/api_methods.py
musichelper/constants/api_urls.py
musichelper/constants/image_hosts.py
musichelper/constants/networking_settings.py
musichelper/constants/search_types.py
musichelper/constants/track_formats.py
music_helper-1.0.9.dist-info/METADATA
music_helper-1.0.9.dist-info/WHEEL
music_helper-1.0.9.dist-info/top_level.txt
music_helper-1.0.9.dist-info/RECORD
