Metadata-Version: 2.1
Name: music-helper
Version: 1.0.9
Summary: Asynchronous library for working with streaming services. Search, download
Home-page: https://github.com/drhspfn/music-helper
Author: drhspfn
Author-email: drhspfn@gmail.com
Classifier: Programming Language :: Python :: 3
Classifier: Operating System :: OS Independent
Requires-Dist: aiofiles
Requires-Dist: soundcloud-v2
Requires-Dist: cryptography
Requires-Dist: mutagen
Requires-Dist: eyed3
Requires-Dist: pytube
Requires-Dist: ytmusicapi
Requires-Dist: httpx[http2]
Requires-Dist: yarl
Requires-Dist: asyncio
